LICENSE.txt
MANIFEST.in
README.md
requirements.txt
setup.py
DTL/__init__.py
DTL/settings.json
DTL/settings.py
DTL.egg-info/PKG-INFO
DTL.egg-info/SOURCES.txt
DTL.egg-info/dependency_links.txt
DTL.egg-info/not-zip-safe
DTL.egg-info/requires.txt
DTL.egg-info/top_level.txt
DTL/api/__init__.py
DTL/api/apiUtils.py
DTL/api/bases.py
DTL/api/daemon.py
DTL/api/decorators.py
DTL/api/document.py
DTL/api/dotifydict.py
DTL/api/enum.py
DTL/api/envUtils.py
DTL/api/exceptions.py
DTL/api/importlib.py
DTL/api/loggingUtils.py
DTL/api/mailer.py
DTL/api/mathUtils.py
DTL/api/path.py
DTL/api/pkgUtils.py
DTL/api/threadlib.py
DTL/api/validate.py
DTL/api/version.py
DTL/api/xmldocument.py
DTL/db/__init__.py
DTL/db/base.py
DTL/db/data.py
DTL/db/properties.py
DTL/db/models/__init__.py
DTL/db/models/graphicsmodels.py
DTL/db/models/listmodel.py
DTL/db/models/scenegraphmodel.py
DTL/db/models/tablemodel.py
DTL/django/__init__.py
DTL/django/default_settings.py
DTL/django/djangoUtils.py
DTL/django/manage.py
DTL/django/urls.py
DTL/django/views.py
DTL/django/wsgi.py
DTL/dropbox/__init__.py
DTL/dropbox/core.py
DTL/gui/__init__.py
DTL/gui/base.py
DTL/gui/dialog.py
DTL/gui/guiUtils.py
DTL/gui/widget.py
DTL/gui/window.py
DTL/gui/wizard.py
DTL/gui/core/__init__.py
DTL/gui/core/external/__init__.py
DTL/gui/core/external/core.py
DTL/gui/core/maya/__init__.py
DTL/gui/core/maya/core.py
DTL/gui/core/motionbuilder/__init__.py
DTL/gui/core/motionbuilder/core.py
DTL/gui/core/studiomax/__init__.py
DTL/gui/core/studiomax/core.py
DTL/gui/widgets/__init__.py
DTL/gui/widgets/choicewidget.py
DTL/gui/widgets/colorpickerwidget.py
DTL/gui/widgets/loginwidget.py
DTL/gui/widgets/pathwidget.py
DTL/gui/widgets/progresswidget.py
DTL/gui/widgets/propertieseditor.py
DTL/gui/widgets/views/choicewidget.ui
DTL/gui/widgets/views/floattransformnodeeditor.ui
DTL/gui/widgets/views/inttransformnodeeditor.ui
DTL/gui/widgets/views/layereditor.ui
DTL/gui/widgets/views/loginwidget.ui
DTL/gui/widgets/views/nodeeditor.ui
DTL/gui/widgets/views/pathwidget.ui
DTL/gui/widgets/views/progresswidget.ui
DTL/gui/widgets/views/propertieseditor.ui
DTL/maya/__init__.py
DTL/maya/mayaUtils.py
DTL/maya/selection.py
