Metadata-Version: 1.1
Name: DTL
Version: 1.1.6
Summary: Multiplatform tools development api
Home-page: https://github.com/rocktavious/DevToolsLib
Author: Kyle Rockman
Author-email: kyle.rockman@mac.com
License: Copyright (c) 2013 Kyle Rockman
